{
  "$schema": "http://json.schemastore.org/template",
  "author": "API Template Pack",
  "name": "Basic Crud Endpoints template",
  "description": "Query request for Vertical Slice Architecture",
  "identity": "CRUD Endpoints",
  "shortName": "crud",
  "sourceName" :"Crud",
  "preferNameDirectory": "true",
  "tags": {
    "language": "C#",
    "type": "item"
  },
  "symbols": {
    "operationid" :{
      "type": "generated",
      "generator": "guid",
      "replaces": "operationid",
      "parameters": {
        "defaultFormat":"d"
      }
    },
    "namespace": {
      "type": "parameter",
      "replaces": "Namespace",
      "dataType": "string",
      "defaultValue": "Namespace"
    },
    "resource": {
      "type": "parameter",
      "replaces": "Resource",
      "dataType": "string",
      "defaultValue": "Resource"
    },
    "model": {
      "type": "parameter",
      "replaces": "Model",
      "dataType": "string",
      "defaultValue": "Model"
    },
    "domain": {
      "type": "parameter",
      "replaces": "Domain",
      "dataType": "string",
      "defaultValue": "Domain"
    }
    
  },
  "classifications": [
    "webapi", "cqrs", "vertical slice", "crud", "endpoints"
  ]
}
